Metadata-Version: 1.1
Name: schemes
Version: 0.1
Summary: Easy input validation and data manipulation.
Home-page: https://bitbucket.org/tawmas/schemes
Author: Tommaso R. Donnarumma
Author-email: tawmas@tawmas.net
License: MIT License
Platform: any
Classifier: Development Status :: 3 - Alpha
Classifier: Intended Audience :: Developers
Classifier: License :: OSI Approved :: MIT License
Classifier: Natural Language :: English
Classifier: Operating System :: OS Independent
Classifier: Programming Language :: Python
Classifier: Programming Language :: Python :: 2
Classifier: Programming Language :: Python :: 2.7
Classifier: Topic :: Software Development :: Libraries
Classifier: Topic :: Software Development :: Libraries :: Python Modules
